{
    "((1,1),(7,9))":[
        0,
        381,
        0
    ],
    "((1,2),(7,9))":[
        0,
        941,
        11
    ],
    "((1,3),(7,9))":[
        0,
        381,
        0
    ],
    "((2,1),(7,9))":[
        0,
        381,
        0
    ],
    "((2,2),(7,9))":[
        0,
        381,
        0
    ],
    "((2,3),(7,9))":[
        0,
        381,
        0
    ],
    "((2,4),(7,9))":[
        0,
        381,
        0
    ],
    "((2,5),(7,9))":[
        0,
        381,
        0
    ],
    "((2,6),(7,9))":[
        0,
        10,
        38401
    ],
    "((2,7),(7,9))":[
        0,
        381,
        0
    ],
    "((3,1),(7,9))":[
        0,
        381,
        0
    ],
    "((3,2),(7,9))":[
        0,
        381,
        0
    ],
    "((3,3),(7,9))":[
        0,
        381,
        0
    ],
    "((3,4),(7,9))":[
        0,
        381,
        0
    ],
    "((3,5),(7,9))":[
        0,
        381,
        0
    ],
    "((3,6),(7,9))":[
        0,
        2230,
        68
    ],
    "((3,7),(7,9))":[
        0,
        381,
        0
    ],
    "((3,8),(7,9))":[
        381,
        0,
        0
    ],
    "((3,9),(7,9))":[
        0,
        381,
        0
    ],
    "((3,10),(7,9))":[
        190,
        5160,
        7
    ],
    "((3,11),(7,9))":[
        0,
        381,
        0
    ],
    "((3,12),(7,9))":[
        15917,
        20710,
        1166
    ],
    "((4,1),(7,9))":[
        0,
        381,
        0
    ],
    "((4,2),(7,9))":[
        30,
        2674,
        39
    ],
    "((4,3),(7,9))":[
        0,
        381,
        0
    ],
    "((4,4),(7,9))":[
        381,
        0,
        0
    ],
    "((4,5),(7,9))":[
        0,
        381,
        0
    ],
    "((4,6),(7,9))":[
        190,
        5160,
        7
    ],
    "((4,7),(7,9))":[
        381,
        0,
        0
    ],
    "((4,8),(7,9))":[
        0,
        381,
        0
    ],
    "((4,9),(7,9))":[
        0,
        0,
        38411
    ],
    "((4,10),(7,9))":[
        0,
        381,
        0
    ],
    "((4,11),(7,9))":[
        136,
        4434,
        9
    ],
    "((4,12),(7,9))":[
        0,
        381,
        0
    ],
    "((4,13),(7,9))":[
        381,
        0,
        0
    ],
    "((4,14),(7,9))":[
        0,
        1894,
        49
    ],
    "((4,15),(7,9))":[
        0,
        0,
        38411
    ],
    "((4,16),(7,9))":[
        0,
        381,
        0
    ],
    "((4,17),(7,9))":[
        0,
        381,
        0
    ],
    "((4,18),(7,9))":[
        5740,
        15404,
        14434
    ],
    "((5,1),(7,9))":[
        381,
        0,
        0
    ],
    "((5,2),(7,9))":[
        381,
        0,
        0
    ],
    "((5,3),(7,9))":[
        381,
        0,
        0
    ],
    "((5,4),(7,9))":[
        0,
        381,
        0
    ],
    "((5,5),(7,9))":[
        0,
        665,
        5
    ],
    "((5,6),(7,9))":[
        0,
        381,
        0
    ],
    "((5,7),(7,9))":[
        381,
        0,
        0
    ],
    "((5,8),(7,9))":[
        0,
        381,
        0
    ],
    "((5,9),(7,9))":[
        381,
        0,
        0
    ],
    "((5,10),(7,9))":[
        55,
        3546,
        69
    ],
    "((5,11),(7,9))":[
        381,
        0,
        0
    ],
    "((5,12),(7,9))":[
        0,
        381,
        0
    ],
    "((5,13),(7,9))":[
        381,
        0,
        0
    ],
    "((5,14),(7,9))":[
        0,
        381,
        0
    ],
    "((5,15),(7,9))":[
        0,
        381,
        0
    ],
    "((5,16),(7,9))":[
        0,
        381,
        0
    ],
    "((5,17),(7,9))":[
        0,
        381,
        0
    ],
    "((5,18),(7,9))":[
        0,
        381,
        0
    ],
    "((5,19),(7,9))":[
        0,
        381,
        0
    ],
    "((5,20),(7,9))":[
        0,
        381,
        0
    ],
    "((6,1),(7,9))":[
        1137,
        12799,
        973
    ],
    "((6,2),(7,9))":[
        381,
        0,
        0
    ],
    "((6,3),(7,9))":[
        0,
        381,
        0
    ],
    "((6,4),(7,9))":[
        0,
        381,
        0
    ],
    "((6,5),(7,9))":[
        0,
        10512,
        24421
    ],
    "((6,6),(7,9))":[
        0,
        381,
        0
    ],
    "((6,7),(7,9))":[
        0,
        5708,
        31814
    ],
    "((6,8),(7,9))":[
        0,
        0,
        38411
    ],
    "((6,9),(7,9))":[
        0,
        381,
        0
    ],
    "((6,10),(7,9))":[
        381,
        0,
        0
    ],
    "((6,11),(7,9))":[
        0,
        381,
        0
    ],
    "((6,12),(7,9))":[
        0,
        381,
        0
    ],
    "((6,13),(7,9))":[
        381,
        0,
        0
    ],
    "((6,14),(7,9))":[
        0,
        381,
        0
    ],
    "((6,15),(7,9))":[
        0,
        381,
        0
    ],
    "((6,16),(7,9))":[
        1061,
        12548,
        974
    ],
    "((6,17),(7,9))":[
        381,
        0,
        0
    ],
    "((6,18),(7,9))":[
        0,
        6597,
        30606
    ],
    "((7,1),(7,9))":[
        0,
        381,
        0
    ],
    "((7,2),(7,9))":[
        13982,
        175,
        16426
    ],
    "((7,3),(7,9))":[
        381,
        0,
        0
    ],
    "((7,4),(7,9))":[
        1065,
        12525,
        944
    ],
    "((7,5),(7,9))":[
        0,
        1887,
        36431
    ],
    "((7,6),(7,9))":[
        0,
        4447,
        33435
    ],
    "((7,7),(7,9))":[
        14499,
        520,
        15140
    ],
    "((7,8),(7,9))":[
        12592,
        31,
        20144
    ],
    "((7,9),(7,10))":[
        0,
        381,
        0
    ],
    "((7,9),(7,11))":[
        381,
        0,
        0
    ],
    "((7,9),(7,12))":[
        1887,
        0,
        36431
    ],
    "((7,9),(8,1))":[
        63,
        14525,
        13977
    ],
    "((7,9),(8,2))":[
        0,
        381,
        0
    ],
    "((7,9),(8,3))":[
        6,
        14383,
        7597
    ],
    "((7,9),(8,4))":[
        63,
        14525,
        13977
    ],
    "((7,9),(8,5))":[
        450,
        12494,
        20479
    ],
    "((7,9),(8,6))":[
        98,
        2719,
        35414
    ],
    "((7,9),(8,7))":[
        0,
        2676,
        35547
    ],
    "((7,9),(8,8))":[
        0,
        1477,
        29
    ],
    "((7,9),(8,9))":[
        0,
        769,
        7
    ],
    "((7,9),(8,10))":[
        0,
        1085,
        15
    ]
}